optimizeai/__init__.py
optimizeai/__main__.py
optimizeai/config.py
optimizeai/cot.py
optimizeai/decorators/__init__.py
optimizeai/decorators/optimize.py
optimizeai/llm_wrapper.py
optimizeai/pdf_utils.py
optimizeai-1.0.0.dist-info/LICENSE
optimizeai-1.0.0.dist-info/METADATA
optimizeai-1.0.0.dist-info/WHEEL
optimizeai-1.0.0.dist-info/RECORD
