Metadata-Version: 2.1
Name: optimizeai
Version: 1.0.0
Summary: OptimAI is a powerful Python module designed to optimize your code by analyzing its performance and providing actionable suggestions. It leverages a large language model (LLM) to give you detailed insights and recommendations based on the profiling data collected during the execution of your code.
Author: Vidhu Mathur
Author-email: vidhumathur2002@gmail.com
Requires-Python: >=3.11,<4.0
Classifier: Programming Language :: Python :: 3
Classifier: Programming Language :: Python :: 3.11
Classifier: Programming Language :: Python :: 3.12
Requires-Dist: accelerate (>=0.31.0,<0.32.0)
Requires-Dist: anthropic (>=0.28.1,<0.29.0)
Requires-Dist: dspy (>=0.1.5,<0.2.0)
Requires-Dist: google (>=3.0.0,<4.0.0)
Requires-Dist: google-generativeai (>=0.7.1,<0.8.0)
Requires-Dist: huggingface (>=0.0.1,<0.0.2)
Requires-Dist: huggingface-hub (>=0.23.3,<0.24.0)
Requires-Dist: langchain (>=0.2.3,<0.3.0)
Requires-Dist: markdown2 (>=2.5.0,<3.0.0)
Requires-Dist: openai (>=1.33.0,<2.0.0)
Requires-Dist: perfwatch (>=1.3.2,<2.0.0)
Requires-Dist: py-context (>=0.3.1,<0.4.0)
Requires-Dist: python-dotenv (>=1.0.1,<2.0.0)
Requires-Dist: reportlab (>=4.2.2,<5.0.0)
Requires-Dist: requests (>=2.32.3,<3.0.0)
Requires-Dist: torch (>=2.3.1,<3.0.0)
Requires-Dist: transformers (>=4.41.2,<5.0.0)
